migrator/main.py
migrator/queries/create_base_value.sql
migrator/queries/get_current_version.sql
migrator/queries/init.sql
migrator/queries/update_migration_schema.sql
migrator/src/db.py
migrator/src/utils.py
pgrate-0.1.1.data/data/queries/create_base_value.sql
pgrate-0.1.1.data/data/queries/get_current_version.sql
pgrate-0.1.1.data/data/queries/init.sql
pgrate-0.1.1.data/data/queries/update_migration_schema.sql
pgrate-0.1.1.dist-info/LICENCE
pgrate-0.1.1.dist-info/METADATA
pgrate-0.1.1.dist-info/WHEEL
pgrate-0.1.1.dist-info/entry_points.txt
pgrate-0.1.1.dist-info/top_level.txt
pgrate-0.1.1.dist-info/RECORD
